{
  "ok": 1,
  "data": {
    "cards": [
      {
        "show_type": 0,
        "title": "实时热点，每分钟更新一次",
        "card_type": 11,
        "itemid": "hotword",
        "card_group": [
          {
            "card_type": 4,
            "pic": "https://simg.s.weibo.com/20180205110043_img_search_stick%403x.png",
            "itemid": "hotword",
            "actionlog": {
              "act_code": 554,
              "ext": "t:51|pos:0_0|c_type:51|cate:10113|page:1|type:25",
              "luicode": "",
              "fid": "106003type=25&t=3&disable_hot=1&filter_type=realtimehot",
              "lfid": "",
              "uicode": 10000003
            },
            "scheme": "https://m.weibo.cn/search?containerid=100103type%3D1%26t%3D10%26q%3D%23%E4%B8%A4%E4%BC%9A%E9%AB%98%E9%A2%91%E8%AF%8D%E5%85%AD%E4%BF%9D%23&isnewpage=1&extparam=pos%3D0%26c_type%3D51%26filter_type%3Drealtimehot%26cate%3D10103%26display_time%3D1590252475&luicode=10000011&lfid=106003type%3D25%26t%3D3%26disable_hot%3D1%26filter_type%3Drealtimehot",
            "desc": "两会高频词六保",
            "icon": "https://simg.s.weibo.com/20190429_hot.png"
          },
          {
            "actionlog": {
              "act_code": 554,
              "ext": "t:31|pos:1_0|c_type:31|cate:10103|page:1|type:25",
              "luicode": "",
              "fid": "106003type=25&t=3&disable_hot=1&filter_type=realtimehot",
              "lfid": "",
              "uicode": 10000003
            },
            "itemid": "hotword",
            "icon": "https://simg.s.weibo.com/20190429_fei.png",
            "desc_extr": "1720734",
            "card_type": 4,
            "scheme": "https://m.weibo.cn/search?containerid=100103type%3D1%26t%3D10%26q%3D%E5%88%98%E9%9B%A8%E6%98%95%E9%95%BF%E5%8F%91&isnewpage=1&extparam=cate%3D0%26pos%3D0%26realpos%3D1%26flag%3D16%26filter_type%3Drealtimehot%26c_type%3D31%26display_time%3D1590252475&luicode=10000011&lfid=106003type%3D25%26t%3D3%26disable_hot%3D1%26filter_type%3Drealtimehot",
            "desc": "刘雨昕长发",
            "pic": "https://simg.s.weibo.com/20170303_img_search_1.png"
          },
          {
            "actionlog": {
              "act_code": 554,
              "ext": "t:31|pos:1_1|c_type:31|cate:10103|page:1|type:25",
              "luicode": "",
              "fid": "106003type=25&t=3&disable_hot=1&filter_type=realtimehot",
              "lfid": "",
              "uicode": 10000003
            },
            "desc_extr": "1389915",
            "pic": "https://simg.s.weibo.com/20170303_img_search_2.png",
            "card_type": 4,
            "scheme": "https://m.weibo.cn/search?containerid=100103type%3D1%26t%3D10%26q%3D%23%E6%BE%B3%E5%A4%A7%E5%88%A9%E4%BA%9A%E6%9A%82%E5%81%9C%E7%94%B3%E5%8A%9E2032%E5%A5%A5%E8%BF%90%23&isnewpage=1&extparam=cate%3D0%26pos%3D1%26realpos%3D2%26flag%3D0%26filter_type%3Drealtimehot%26c_type%3D31%26display_time%3D1590252475&luicode=10000011&lfid=106003type%3D25%26t%3D3%26disable_hot%3D1%26filter_type%3Drealtimehot",
            "desc": "澳大利亚暂停申办2032奥运",
            "itemid": "hotword"
          },
          {
            "actionlog": {
              "act_code": 554,
              "ext": "t:31|pos:1_2|c_type:31|ads_word:#哎哟不错奥利奥#|adid:83866|cate:10103|page:1|type:25",
              "luicode": "",
              "fid": "106003type=25&t=3&disable_hot=1&filter_type=realtimehot",
              "lfid": "",
              "uicode": 10000003
            },
            "itemid": "hotword",
            "promotion": {
              "monitor_url": []
            },
            "icon": "https://simg.s.weibo.com/20190429_recom.png",
            "desc_extr": 1317348,
            "card_type": 4,
            "scheme": "https://m.weibo.cn/search?containerid=100103type%3D1%26t%3D10%26q%3D%23%E5%93%8E%E5%93%9F%E4%B8%8D%E9%94%99%E5%A5%A5%E5%88%A9%E5%A5%A5%23&isnewpage=1&extparam=cate%3D0%26pos%3D2%26topic_ad%3D1%26filter_type%3Drealtimehot%26c_type%3D31%26display_time%3D1590252475&luicode=10000011&lfid=106003type%3D25%26t%3D3%26disable_hot%3D1%26filter_type%3Drealtimehot",
            "desc": "哎哟不错奥利奥",
            "pic": "https://simg.s.weibo.com/20170303_img_search_3.png"
          },
          {
            "actionlog": {
              "act_code": 554,
              "ext": "t:31|pos:1_3|c_type:31|cate:10103|page:1|type:25",
              "luicode": "",
              "fid": "106003type=25&t=3&disable_hot=1&filter_type=realtimehot",
              "lfid": "",
              "uicode": 10000003
            },
            "itemid": "hotword",
            "icon": "https://simg.s.weibo.com/20190429_hot.png",
            "desc_extr": "1148024",
            "card_type": 4,
            "scheme": "https://m.weibo.cn/search?containerid=100103type%3D1%26t%3D10%26q%3D%23%E5%90%B4%E6%98%95%E8%B7%B3%E8%88%9E%23&isnewpage=1&extparam=cate%3D0%26pos%3D3%26realpos%3D3%26flag%3D2%26filter_type%3Drealtimehot%26c_type%3D31%26display_time%3D1590252475&luicode=10000011&lfid=106003type%3D25%26t%3D3%26disable_hot%3D1%26filter_type%3Drealtimehot",
            "desc": "吴昕跳舞",
            "pic": "https://simg.s.weibo.com/20170303_img_search_4.png"
          },
          {
            "actionlog": {
              "act_code": 554,
              "ext": "t:31|pos:1_4|c_type:31|cate:10103|page:1|type:25",
              "luicode": "",
              "fid": "106003type=25&t=3&disable_hot=1&filter_type=realtimehot",
              "lfid": "",
              "uicode": 10000003
            },
            "itemid": "hotword",
            "icon": "https://simg.s.weibo.com/20190429_fei.png",
            "desc_extr": "1094311",
            "card_type": 4,
            "scheme": "https://m.weibo.cn/search?containerid=100103type%3D1%26t%3D10%26q%3D%23%E4%B9%83%E4%B8%87%E7%94%A9%E8%AF%9D%E7%AD%92%23&isnewpage=1&extparam=cate%3D0%26pos%3D4%26realpos%3D4%26flag%3D16%26filter_type%3Drealtimehot%26c_type%3D31%26display_time%3D1590252475&luicode=10000011&lfid=106003type%3D25%26t%3D3%26disable_hot%3D1%26filter_type%3Drealtimehot",
            "desc": "乃万甩话筒",
            "pic": "https://simg.s.weibo.com/20170303_img_search_5.png"
          },
          {
            "actionlog": {
              "act_code": 554,
              "ext": "t:31|pos:1_5|c_type:31|cate:10103|page:1|type:25",
              "luicode": "",
              "fid": "106003type=25&t=3&disable_hot=1&filter_type=realtimehot",
              "lfid": "",
              "uicode": 10000003
            },
            "desc_extr": "655005",
            "pic": "https://simg.s.weibo.com/20170303_img_search_6.png",
            "card_type": 4,
            "scheme": "https://m.weibo.cn/search?containerid=100103type%3D1%26t%3D10%26q%3D%23%E6%9C%89%E6%B2%A1%E6%9C%89%E4%B8%80%E7%A7%8D%E5%B0%8F%E9%BE%99%E8%99%BE%E6%98%AF%E8%93%AC%E6%9D%BE%E7%9A%84%23&isnewpage=1&extparam=cate%3D0%26pos%3D5%26realpos%3D5%26flag%3D0%26filter_type%3Drealtimehot%26c_type%3D31%26display_time%3D1590252475&luicode=10000011&lfid=106003type%3D25%26t%3D3%26disable_hot%3D1%26filter_type%3Drealtimehot",
            "desc": "有没有一种小龙虾是蓬松的",
            "itemid": "hotword"
          },
          {
            "actionlog": {
              "act_code": 554,
              "ext": "t:31|pos:1_6|c_type:31|cate:10103|page:1|type:25",
              "luicode": "",
              "fid": "106003type=25&t=3&disable_hot=1&filter_type=realtimehot",
              "lfid": "",
              "uicode": 10000003
            },
            "itemid": "hotword",
            "icon": "https://simg.s.weibo.com/20190429_fei.png",
            "desc_extr": "641862",
            "card_type": 4,
            "scheme": "https://m.weibo.cn/search?containerid=100103type%3D1%26t%3D10%26q%3D%23%E9%9D%92%E6%98%A5%E6%9C%89%E4%BD%A0%E5%AF%BC%E5%B8%88%E5%90%88%E4%BD%9C%E8%88%9E%E5%8F%B0%23&isnewpage=1&extparam=cate%3D0%26pos%3D6%26realpos%3D6%26flag%3D16%26filter_type%3Drealtimehot%26c_type%3D31%26display_time%3D1590252475&luicode=10000011&lfid=106003type%3D25%26t%3D3%26disable_hot%3D1%26filter_type%3Drealtimehot",
            "desc": "青春有你导师合作舞台",
            "pic": "https://simg.s.weibo.com/20170303_img_search_7.png"
          },
          {
            "actionlog": {
              "act_code": 554,
              "ext": "t:31|pos:1_7|c_type:31|cate:10103|page:1|type:25",
              "luicode": "",
              "fid": "106003type=25&t=3&disable_hot=1&filter_type=realtimehot",
              "lfid": "",
              "uicode": 10000003
            },
            "itemid": "hotword",
            "icon": "https://simg.s.weibo.com/20190429_new.png",
            "desc_extr": "464023",
            "card_type": 4,
            "scheme": "https://m.weibo.cn/search?containerid=100103type%3D1%26t%3D10%26q%3D%23%E6%BE%B3%E9%97%A8%E7%89%B9%E5%8C%BA%E6%94%BF%E5%BA%9C%E5%9D%9A%E5%86%B3%E6%94%AF%E6%8C%81%E4%B8%AD%E5%A4%AE%E5%86%B3%E5%AE%9A%23&isnewpage=1&extparam=cate%3D0%26pos%3D7%26realpos%3D7%26flag%3D1%26filter_type%3Drealtimehot%26c_type%3D31%26display_time%3D1590252475&luicode=10000011&lfid=106003type%3D25%26t%3D3%26disable_hot%3D1%26filter_type%3Drealtimehot",
            "desc": "澳门特区政府坚决支持中央决定",
            "pic": "https://simg.s.weibo.com/20170303_img_search_8.png"
          },
          {
            "actionlog": {
              "act_code": 554,
              "ext": "t:31|pos:1_8|c_type:31|cate:10103|page:1|type:25",
              "luicode": "",
              "fid": "106003type=25&t=3&disable_hot=1&filter_type=realtimehot",
              "lfid": "",
              "uicode": 10000003
            },
            "itemid": "hotword",
            "icon": "https://simg.s.weibo.com/20190429_hot.png",
            "desc_extr": "342777",
            "card_type": 4,
            "scheme": "https://m.weibo.cn/search?containerid=100103type%3D1%26t%3D10%26q%3D%23%E9%9F%A9%E5%9B%BD%E6%A2%A8%E6%B3%B0%E9%99%A2%E6%84%9F%E6%9F%93%E4%BA%8B%E4%BB%B6%E7%97%85%E6%AF%92%E7%B1%BB%E5%9E%8B%E4%B8%8E%E6%AC%A7%E7%BE%8E%E5%90%BB%E5%90%88%23&isnewpage=1&extparam=cate%3D0%26pos%3D8%26realpos%3D8%26flag%3D2%26filter_type%3Drealtimehot%26c_type%3D31%26display_time%3D1590252475&luicode=10000011&lfid=106003type%3D25%26t%3D3%26disable_hot%3D1%26filter_type%3Drealtimehot",
            "desc": "韩国梨泰院感染事件病毒类型与欧美吻合",
            "pic": "https://simg.s.weibo.com/20170303_img_search_9.png"
          },
          {
            "actionlog": {
              "act_code": 554,
              "ext": "t:31|pos:1_9|c_type:31|cate:10103|page:1|type:25",
              "luicode": "",
              "fid": "106003type=25&t=3&disable_hot=1&filter_type=realtimehot",
              "lfid": "",
              "uicode": 10000003
            },
            "itemid": "hotword",
            "icon": "https://simg.s.weibo.com/20190429_new.png",
            "desc_extr": "341084",
            "card_type": 4,
            "scheme": "https://m.weibo.cn/search?containerid=100103type%3D1%26t%3D10%26q%3D%E6%9C%9F%E5%BE%85Lisa%E7%BB%84&isnewpage=1&extparam=cate%3D0%26pos%3D9%26realpos%3D9%26flag%3D1%26filter_type%3Drealtimehot%26c_type%3D31%26display_time%3D1590252475&luicode=10000011&lfid=106003type%3D25%26t%3D3%26disable_hot%3D1%26filter_type%3Drealtimehot",
            "desc": "期待Lisa组",
            "pic": "https://simg.s.weibo.com/20170303_img_search_10.png"
          },
          {
            "actionlog": {
              "act_code": 554,
              "ext": "t:31|pos:1_10|c_type:31|cate:10103|page:1|type:25",
              "luicode": "",
              "fid": "106003type=25&t=3&disable_hot=1&filter_type=realtimehot",
              "lfid": "",
              "uicode": 10000003
            },
            "desc_extr": "338701",
            "pic": "https://simg.s.weibo.com/20170303_img_search_11.png",
            "card_type": 4,
            "scheme": "https://m.weibo.cn/search?containerid=100103type%3D1%26t%3D10%26q%3D%E8%B5%AB%E5%85%B9%E4%B8%AD%E5%9B%BD%E5%9B%9E%E5%BA%94%E7%94%B3%E8%AF%B7%E7%A0%B4%E4%BA%A7&isnewpage=1&extparam=cate%3D0%26pos%3D10%26realpos%3D10%26flag%3D0%26filter_type%3Drealtimehot%26c_type%3D31%26display_time%3D1590252475&luicode=10000011&lfid=106003type%3D25%26t%3D3%26disable_hot%3D1%26filter_type%3Drealtimehot",
            "desc": "赫兹中国回应申请破产",
            "itemid": "hotword"
          },
          {
            "actionlog": {
              "act_code": 554,
              "ext": "t:31|pos:1_11|c_type:31|cate:10103|page:1|type:25",
              "luicode": "",
              "fid": "106003type=25&t=3&disable_hot=1&filter_type=realtimehot",
              "lfid": "",
              "uicode": 10000003
            },
            "desc_extr": "337612",
            "pic": "https://simg.s.weibo.com/20170303_img_search_12.png",
            "card_type": 4,
            "scheme": "https://m.weibo.cn/search?containerid=100103type%3D1%26t%3D10%26q%3D%23%E5%9B%BD%E6%BC%AB%E8%A6%81%E8%B5%B0%E5%87%BA%E4%B8%AD%E5%9B%BD%E9%81%93%E8%B7%AF%23&isnewpage=1&extparam=cate%3D0%26pos%3D11%26realpos%3D11%26flag%3D0%26filter_type%3Drealtimehot%26c_type%3D31%26display_time%3D1590252475&luicode=10000011&lfid=106003type%3D25%26t%3D3%26disable_hot%3D1%26filter_type%3Drealtimehot",
            "desc": "国漫要走出中国道路",
            "itemid": "hotword"
          },
          {
            "actionlog": {
              "act_code": 554,
              "ext": "t:31|pos:1_12|c_type:31|cate:10103|page:1|type:25",
              "luicode": "",
              "fid": "106003type=25&t=3&disable_hot=1&filter_type=realtimehot",
              "lfid": "",
              "uicode": 10000003
            },
            "itemid": "hotword",
            "icon": "https://simg.s.weibo.com/20190429_new.png",
            "desc_extr": "336544",
            "card_type": 4,
            "scheme": "https://m.weibo.cn/search?containerid=100103type%3D1%26t%3D10%26q%3D%E5%89%8DCUBA%E7%AF%AE%E7%90%83%E9%98%9F%E5%91%98%E5%8F%82%E5%86%9B%E6%8A%A4%E8%88%AA%E4%BA%9A%E4%B8%81%E6%B9%BE&isnewpage=1&extparam=cate%3D0%26pos%3D12%26realpos%3D12%26flag%3D1%26filter_type%3Drealtimehot%26c_type%3D31%26display_time%3D1590252475&luicode=10000011&lfid=106003type%3D25%26t%3D3%26disable_hot%3D1%26filter_type%3Drealtimehot",
            "desc": "前CUBA篮球队员参军护航亚丁湾",
            "pic": "https://simg.s.weibo.com/20170303_img_search_13.png"
          },
          {
            "actionlog": {
              "act_code": 554,
              "ext": "t:31|pos:1_13|c_type:31|cate:10103|page:1|type:25",
              "luicode": "",
              "fid": "106003type=25&t=3&disable_hot=1&filter_type=realtimehot",
              "lfid": "",
              "uicode": 10000003
            },
            "desc_extr": "335071",
            "pic": "https://simg.s.weibo.com/20170303_img_search_14.png",
            "card_type": 4,
            "scheme": "https://m.weibo.cn/search?containerid=100103type%3D1%26t%3D10%26q%3D%23%E5%90%89%E6%9E%97%E5%B0%81%E9%97%AD%E5%B0%8F%E5%8C%BA%E5%B1%85%E6%B0%91%E7%94%A8%E8%94%AC%E8%8F%9C%E6%91%86%E6%84%9F%E8%B0%A2%E8%AF%AD%23&isnewpage=1&extparam=cate%3D0%26pos%3D13%26realpos%3D13%26flag%3D0%26filter_type%3Drealtimehot%26c_type%3D31%26display_time%3D1590252475&luicode=10000011&lfid=106003type%3D25%26t%3D3%26disable_hot%3D1%26filter_type%3Drealtimehot",
            "desc": "吉林封闭小区居民用蔬菜摆感谢语",
            "itemid": "hotword"
          },
          {
            "actionlog": {
              "act_code": 554,
              "ext": "t:31|pos:1_14|c_type:31|cate:10103|page:1|type:25",
              "luicode": "",
              "fid": "106003type=25&t=3&disable_hot=1&filter_type=realtimehot",
              "lfid": "",
              "uicode": 10000003
            },
            "desc_extr": "334395",
            "pic": "https://simg.s.weibo.com/20170303_img_search_15.png",
            "card_type": 4,
            "scheme": "https://m.weibo.cn/search?containerid=100103type%3D1%26t%3D10%26q%3D%23%E7%88%B6%E4%BA%B2%E6%94%B6%E5%88%B0%E5%A5%B3%E5%84%BF%E9%80%81%E7%9A%84%E8%89%B2%E7%9B%B2%E7%9C%BC%E9%95%9C%23&isnewpage=1&extparam=cate%3D0%26pos%3D14%26realpos%3D14%26flag%3D0%26filter_type%3Drealtimehot%26c_type%3D31%26display_time%3D1590252475&luicode=10000011&lfid=106003type%3D25%26t%3D3%26disable_hot%3D1%26filter_type%3Drealtimehot",
            "desc": "父亲收到女儿送的色盲眼镜",
            "itemid": "hotword"
          },
          {
            "actionlog": {
              "act_code": 554,
              "ext": "t:31|pos:1_15|c_type:31|cate:10103|page:1|type:25",
              "luicode": "",
              "fid": "106003type=25&t=3&disable_hot=1&filter_type=realtimehot",
              "lfid": "",
              "uicode": 10000003
            },
            "itemid": "hotword",
            "icon": "https://simg.s.weibo.com/20190429_hot.png",
            "desc_extr": "332477",
            "card_type": 4,
            "scheme": "https://m.weibo.cn/search?containerid=100103type%3D1%26t%3D10%26q%3D%23%E5%BB%BA%E8%AE%AE%E6%9C%AA%E6%88%90%E5%B9%B4%E4%BA%BA%E4%B8%8D%E8%83%BD%E4%BB%8E%E4%BA%8B%E8%B6%85%E9%BE%84%E5%95%86%E4%B8%9A%E6%B4%BB%E5%8A%A8%23&isnewpage=1&extparam=cate%3D0%26pos%3D15%26realpos%3D15%26flag%3D2%26filter_type%3Drealtimehot%26c_type%3D31%26display_time%3D1590252475&luicode=10000011&lfid=106003type%3D25%26t%3D3%26disable_hot%3D1%26filter_type%3Drealtimehot",
            "desc": "建议未成年人不能从事超龄商业活动",
            "pic": "https://simg.s.weibo.com/20170303_img_search_16.png"
          },
          {
            "actionlog": {
              "act_code": 554,
              "ext": "t:31|pos:1_16|c_type:31|cate:10103|page:1|type:25",
              "luicode": "",
              "fid": "106003type=25&t=3&disable_hot=1&filter_type=realtimehot",
              "lfid": "",
              "uicode": 10000003
            },
            "desc_extr": "331523",
            "pic": "https://simg.s.weibo.com/20170303_img_search_17.png",
            "card_type": 4,
            "scheme": "https://m.weibo.cn/search?containerid=100103type%3D1%26t%3D10%26q%3D%23%E9%AB%98%E4%BC%9F%E5%85%89%E6%83%85%E5%95%86%23&isnewpage=1&extparam=cate%3D0%26pos%3D16%26realpos%3D16%26flag%3D0%26filter_type%3Drealtimehot%26c_type%3D31%26display_time%3D1590252475&luicode=10000011&lfid=106003type%3D25%26t%3D3%26disable_hot%3D1%26filter_type%3Drealtimehot",
            "desc": "高伟光情商",
            "itemid": "hotword"
          },
          {
            "actionlog": {
              "act_code": 554,
              "ext": "t:31|pos:1_17|c_type:31|cate:10103|page:1|type:25",
              "luicode": "",
              "fid": "106003type=25&t=3&disable_hot=1&filter_type=realtimehot",
              "lfid": "",
              "uicode": 10000003
            },
            "itemid": "hotword",
            "icon": "https://simg.s.weibo.com/20190429_new.png",
            "desc_extr": "329082",
            "card_type": 4,
            "scheme": "https://m.weibo.cn/search?containerid=100103type%3D1%26t%3D10%26q%3D%23%E7%BE%8E%E5%9B%BD%E6%84%9F%E6%9F%93%E6%96%B0%E5%86%A0%E7%90%86%E5%8F%91%E5%B8%88%E4%B8%8E91%E4%BA%BA%E6%8E%A5%E8%A7%A6%23&isnewpage=1&extparam=cate%3D0%26pos%3D17%26realpos%3D17%26flag%3D1%26filter_type%3Drealtimehot%26c_type%3D31%26display_time%3D1590252475&luicode=10000011&lfid=106003type%3D25%26t%3D3%26disable_hot%3D1%26filter_type%3Drealtimehot",
            "desc": "美国感染新冠理发师与91人接触",
            "pic": "https://simg.s.weibo.com/20170303_img_search_18.png"
          },
          {
            "actionlog": {
              "act_code": 554,
              "ext": "t:31|pos:1_18|c_type:31|cate:10103|page:1|type:25",
              "luicode": "",
              "fid": "106003type=25&t=3&disable_hot=1&filter_type=realtimehot",
              "lfid": "",
              "uicode": 10000003
            },
            "desc_extr": "328781",
            "pic": "https://simg.s.weibo.com/20170303_img_search_19.png",
            "card_type": 4,
            "scheme": "https://m.weibo.cn/search?containerid=100103type%3D1%26t%3D10%26q%3D%23%E5%A4%A7%E5%AD%A6%E7%94%9F%E6%B4%BB%E8%B4%B9%E6%9C%80%E5%A4%A7%E7%9A%84%E4%B8%80%E7%AC%94%E6%94%AF%E5%87%BA%23&isnewpage=1&extparam=cate%3D0%26pos%3D18%26realpos%3D18%26flag%3D0%26filter_type%3Drealtimehot%26c_type%3D31%26display_time%3D1590252475&luicode=10000011&lfid=106003type%3D25%26t%3D3%26disable_hot%3D1%26filter_type%3Drealtimehot",
            "desc": "大学生活费最大的一笔支出",
            "itemid": "hotword"
          },
          {
            "actionlog": {
              "act_code": 554,
              "ext": "t:31|pos:1_19|c_type:31|cate:10103|page:1|type:25",
              "luicode": "",
              "fid": "106003type=25&t=3&disable_hot=1&filter_type=realtimehot",
              "lfid": "",
              "uicode": 10000003
            },
            "itemid": "hotword",
            "icon": "https://simg.s.weibo.com/20190429_new.png",
            "desc_extr": "327247",
            "card_type": 4,
            "scheme": "https://m.weibo.cn/search?containerid=100103type%3D1%26t%3D10%26q%3D%23%E5%BC%A0%E8%89%BA%E5%87%A1%E5%8F%8D%E4%B8%B2%23&isnewpage=1&extparam=cate%3D0%26pos%3D19%26realpos%3D19%26flag%3D1%26filter_type%3Drealtimehot%26c_type%3D31%26display_time%3D1590252475&luicode=10000011&lfid=106003type%3D25%26t%3D3%26disable_hot%3D1%26filter_type%3Drealtimehot",
            "desc": "张艺凡反串",
            "pic": "https://simg.s.weibo.com/20170303_img_search_20.png"
          },
          {
            "actionlog": {
              "act_code": 554,
              "ext": "t:31|pos:1_20|c_type:31|cate:10103|page:1|type:25",
              "luicode": "",
              "fid": "106003type=25&t=3&disable_hot=1&filter_type=realtimehot",
              "lfid": "",
              "uicode": 10000003
            },
            "desc_extr": "325143",
            "pic": "https://simg.s.weibo.com/20170303_img_search_21.png",
            "card_type": 4,
            "scheme": "https://m.weibo.cn/search?containerid=100103type%3D1%26t%3D10%26q%3D%E5%B9%B8%E7%A6%8F%E8%A7%A6%E6%89%8B%E5%8F%AF%E5%8F%8A&isnewpage=1&extparam=cate%3D0%26pos%3D20%26realpos%3D20%26flag%3D0%26filter_type%3Drealtimehot%26c_type%3D31%26display_time%3D1590252475&luicode=10000011&lfid=106003type%3D25%26t%3D3%26disable_hot%3D1%26filter_type%3Drealtimehot",
            "desc": "幸福触手可及",
            "itemid": "hotword"
          },
          {
            "actionlog": {
              "act_code": 554,
              "ext": "t:31|pos:1_21|c_type:31|cate:10103|page:1|type:25",
              "luicode": "",
              "fid": "106003type=25&t=3&disable_hot=1&filter_type=realtimehot",
              "lfid": "",
              "uicode": 10000003
            },
            "desc_extr": "324613",
            "pic": "https://simg.s.weibo.com/20170303_img_search_22.png",
            "card_type": 4,
            "scheme": "https://m.weibo.cn/search?containerid=100103type%3D1%26t%3D10%26q%3D%E5%88%9B%E9%80%A0%E8%90%A5&isnewpage=1&extparam=cate%3D0%26pos%3D21%26realpos%3D21%26flag%3D0%26filter_type%3Drealtimehot%26c_type%3D31%26display_time%3D1590252475&luicode=10000011&lfid=106003type%3D25%26t%3D3%26disable_hot%3D1%26filter_type%3Drealtimehot",
            "desc": "创造营",
            "itemid": "hotword"
          },
          {
            "actionlog": {
              "act_code": 554,
              "ext": "t:31|pos:1_22|c_type:31|cate:10103|page:1|type:25",
              "luicode": "",
              "fid": "106003type=25&t=3&disable_hot=1&filter_type=realtimehot",
              "lfid": "",
              "uicode": 10000003
            },
            "itemid": "hotword",
            "icon": "https://simg.s.weibo.com/20190429_new.png",
            "desc_extr": "321234",
            "card_type": 4,
            "scheme": "https://m.weibo.cn/search?containerid=100103type%3D1%26t%3D10%26q%3D%23%E5%90%89%E6%9E%97%E5%9B%9B%E5%B9%B3%E6%8B%9F%E7%A6%81%E5%85%BB%E4%B8%AD%E5%8D%8E%E7%94%B0%E5%9B%AD%E7%8A%AC%23&isnewpage=1&extparam=cate%3D0%26pos%3D22%26realpos%3D22%26flag%3D1%26filter_type%3Drealtimehot%26c_type%3D31%26display_time%3D1590252475&luicode=10000011&lfid=106003type%3D25%26t%3D3%26disable_hot%3D1%26filter_type%3Drealtimehot",
            "desc": "吉林四平拟禁养中华田园犬",
            "pic": "https://simg.s.weibo.com/20170303_img_search_23.png"
          },
          {
            "actionlog": {
              "act_code": 554,
              "ext": "t:31|pos:1_23|c_type:31|cate:10103|page:1|type:25",
              "luicode": "",
              "fid": "106003type=25&t=3&disable_hot=1&filter_type=realtimehot",
              "lfid": "",
              "uicode": 10000003
            },
            "desc_extr": "305657",
            "pic": "https://simg.s.weibo.com/20170303_img_search_24.png",
            "card_type": 4,
            "scheme": "https://m.weibo.cn/search?containerid=100103type%3D1%26t%3D10%26q%3D%E9%9F%AB%E8%89%B2%E8%BF%87%E6%B5%93&isnewpage=1&extparam=cate%3D0%26pos%3D23%26realpos%3D23%26flag%3D0%26filter_type%3Drealtimehot%26c_type%3D31%26display_time%3D1590252475&luicode=10000011&lfid=106003type%3D25%26t%3D3%26disable_hot%3D1%26filter_type%3Drealtimehot",
            "desc": "韫色过浓",
            "itemid": "hotword"
          },
          {
            "actionlog": {
              "act_code": 554,
              "ext": "t:31|pos:1_24|c_type:31|cate:10103|page:1|type:25",
              "luicode": "",
              "fid": "106003type=25&t=3&disable_hot=1&filter_type=realtimehot",
              "lfid": "",
              "uicode": 10000003
            },
            "itemid": "hotword",
            "icon": "https://simg.s.weibo.com/20190429_new.png",
            "desc_extr": "305195",
            "card_type": 4,
            "scheme": "https://m.weibo.cn/search?containerid=100103type%3D1%26t%3D10%26q%3D%23%E5%AD%99%E5%A6%82%E4%BA%91p%E5%9B%BE%E5%AE%9E%E5%8A%9B%23&isnewpage=1&extparam=cate%3D0%26pos%3D24%26realpos%3D24%26flag%3D1%26filter_type%3Drealtimehot%26c_type%3D31%26display_time%3D1590252475&luicode=10000011&lfid=106003type%3D25%26t%3D3%26disable_hot%3D1%26filter_type%3Drealtimehot",
            "desc": "孙如云p图实力",
            "pic": "https://simg.s.weibo.com/20170303_img_search_25.png"
          },
          {
            "actionlog": {
              "act_code": 554,
              "ext": "t:31|pos:1_25|c_type:31|cate:10103|page:1|type:25",
              "luicode": "",
              "fid": "106003type=25&t=3&disable_hot=1&filter_type=realtimehot",
              "lfid": "",
              "uicode": 10000003
            },
            "desc_extr": "304718",
            "pic": "https://simg.s.weibo.com/20170303_img_search_26.png",
            "card_type": 4,
            "scheme": "https://m.weibo.cn/search?containerid=100103type%3D1%26t%3D10%26q%3D%23%E5%AD%9F%E9%B9%A4%E5%A0%82%E6%9B%BE%E6%AF%85%E8%B7%B3%E5%A5%B3%E5%9B%A2%E8%88%9E%23&isnewpage=1&extparam=cate%3D0%26pos%3D25%26realpos%3D25%26flag%3D0%26filter_type%3Drealtimehot%26c_type%3D31%26display_time%3D1590252475&luicode=10000011&lfid=106003type%3D25%26t%3D3%26disable_hot%3D1%26filter_type%3Drealtimehot",
            "desc": "孟鹤堂曾毅跳女团舞",
            "itemid": "hotword"
          },
          {
            "actionlog": {
              "act_code": 554,
              "ext": "t:31|pos:1_26|c_type:31|cate:10103|page:1|type:25",
              "luicode": "",
              "fid": "106003type=25&t=3&disable_hot=1&filter_type=realtimehot",
              "lfid": "",
              "uicode": 10000003
            },
            "itemid": "hotword",
            "icon": "https://simg.s.weibo.com/20190429_new.png",
            "desc_extr": "233075",
            "card_type": 4,
            "scheme": "https://m.weibo.cn/search?containerid=100103type%3D1%26t%3D10%26q%3D%23%E7%A6%8F%E5%B7%9E%E5%9C%B0%E9%93%81%E5%A4%9C%E9%97%B4%E5%93%8D%E8%B5%B7%E8%9B%99%E5%A3%B0%23&isnewpage=1&extparam=cate%3D0%26pos%3D26%26realpos%3D26%26flag%3D1%26filter_type%3Drealtimehot%26c_type%3D31%26display_time%3D1590252475&luicode=10000011&lfid=106003type%3D25%26t%3D3%26disable_hot%3D1%26filter_type%3Drealtimehot",
            "desc": "福州地铁夜间响起蛙声",
            "pic": "https://simg.s.weibo.com/20170303_img_search_27.png"
          },
          {
            "actionlog": {
              "act_code": 554,
              "ext": "t:31|pos:1_27|c_type:31|cate:10103|page:1|type:25",
              "luicode": "",
              "fid": "106003type=25&t=3&disable_hot=1&filter_type=realtimehot",
              "lfid": "",
              "uicode": 10000003
            },
            "desc_extr": "222068",
            "pic": "https://simg.s.weibo.com/20170303_img_search_28.png",
            "card_type": 4,
            "scheme": "https://m.weibo.cn/search?containerid=100103type%3D1%26t%3D10%26q%3D%23%E9%A9%AC%E8%B8%8F%E9%A3%9E%E7%87%95%E4%B8%8D%E6%8B%8D%E6%AD%A3%E9%9D%A2%E7%9A%84%E5%8E%9F%E5%9B%A0%23&isnewpage=1&extparam=cate%3D0%26pos%3D27%26realpos%3D27%26flag%3D0%26filter_type%3Drealtimehot%26c_type%3D31%26display_time%3D1590252475&luicode=10000011&lfid=106003type%3D25%26t%3D3%26disable_hot%3D1%26filter_type%3Drealtimehot",
            "desc": "马踏飞燕不拍正面的原因",
            "itemid": "hotword"
          },
          {
            "actionlog": {
              "act_code": 554,
              "ext": "t:31|pos:1_28|c_type:31|cate:10103|page:1|type:25",
              "luicode": "",
              "fid": "106003type=25&t=3&disable_hot=1&filter_type=realtimehot",
              "lfid": "",
              "uicode": 10000003
            },
            "itemid": "hotword",
            "icon": "https://simg.s.weibo.com/20190429_new.png",
            "desc_extr": "205528",
            "card_type": 4,
            "scheme": "https://m.weibo.cn/search?containerid=100103type%3D1%26t%3D10%26q%3D%23%E6%AD%A6%E8%AD%A6%E6%8A%B1%E5%8F%97%E4%BC%A4%E5%A5%B3%E5%AD%A9%E5%88%B0%E5%8C%BB%E9%99%A2%E5%90%8E%E9%BB%98%E9%BB%98%E7%A6%BB%E5%BC%80%23&isnewpage=1&extparam=cate%3D0%26pos%3D28%26realpos%3D28%26flag%3D1%26filter_type%3Drealtimehot%26c_type%3D31%26display_time%3D1590252475&luicode=10000011&lfid=106003type%3D25%26t%3D3%26disable_hot%3D1%26filter_type%3Drealtimehot",
            "desc": "武警抱受伤女孩到医院后默默离开",
            "pic": "https://simg.s.weibo.com/20170303_img_search_29.png"
          },
          {
            "actionlog": {
              "act_code": 554,
              "ext": "t:31|pos:1_29|c_type:31|cate:10103|page:1|type:25",
              "luicode": "",
              "fid": "106003type=25&t=3&disable_hot=1&filter_type=realtimehot",
              "lfid": "",
              "uicode": 10000003
            },
            "desc_extr": "195209",
            "pic": "https://simg.s.weibo.com/20170303_img_search_30.png",
            "card_type": 4,
            "scheme": "https://m.weibo.cn/search?containerid=100103type%3D1%26t%3D10%26q%3D%23%E6%83%85%E4%BA%BA%E8%88%9E%E5%8F%B0%E5%83%8F%E6%8B%8DMV%23&isnewpage=1&extparam=cate%3D0%26pos%3D29%26realpos%3D29%26flag%3D0%26filter_type%3Drealtimehot%26c_type%3D31%26display_time%3D1590252475&luicode=10000011&lfid=106003type%3D25%26t%3D3%26disable_hot%3D1%26filter_type%3Drealtimehot",
            "desc": "情人舞台像拍MV",
            "itemid": "hotword"
          },
          {
            "actionlog": {
              "act_code": 554,
              "ext": "t:31|pos:1_30|c_type:31|cate:10103|page:1|type:25",
              "luicode": "",
              "fid": "106003type=25&t=3&disable_hot=1&filter_type=realtimehot",
              "lfid": "",
              "uicode": 10000003
            },
            "desc_extr": "185885",
            "pic": "https://simg.s.weibo.com/20170303_img_search_31.png",
            "card_type": 4,
            "scheme": "https://m.weibo.cn/search?containerid=100103type%3D1%26t%3D10%26q%3D%E9%BB%84%E5%AD%90%E9%9F%AC&isnewpage=1&extparam=cate%3D0%26pos%3D30%26realpos%3D30%26flag%3D0%26filter_type%3Drealtimehot%26c_type%3D31%26display_time%3D1590252475&luicode=10000011&lfid=106003type%3D25%26t%3D3%26disable_hot%3D1%26filter_type%3Drealtimehot",
            "desc": "黄子韬",
            "itemid": "hotword"
          },
          {
            "actionlog": {
              "act_code": 554,
              "ext": "t:31|pos:1_31|c_type:31|cate:10103|page:1|type:25",
              "luicode": "",
              "fid": "106003type=25&t=3&disable_hot=1&filter_type=realtimehot",
              "lfid": "",
              "uicode": 10000003
            },
            "desc_extr": "177523",
            "pic": "https://simg.s.weibo.com/20170303_img_search_32.png",
            "card_type": 4,
            "scheme": "https://m.weibo.cn/search?containerid=100103type%3D1%26t%3D10%26q%3D%23%E6%95%85%E6%84%8F%E7%BB%8A%E5%80%92%E5%84%BF%E7%AB%A5%E5%B9%BF%E5%9C%BA%E8%88%9E%E8%80%81%E4%BA%BA%E6%89%98%E4%BA%BA%E9%81%93%E6%AD%89%23&isnewpage=1&extparam=cate%3D0%26pos%3D31%26realpos%3D31%26flag%3D0%26filter_type%3Drealtimehot%26c_type%3D31%26display_time%3D1590252475&luicode=10000011&lfid=106003type%3D25%26t%3D3%26disable_hot%3D1%26filter_type%3Drealtimehot",
            "desc": "故意绊倒儿童广场舞老人托人道歉",
            "itemid": "hotword"
          },
          {
            "actionlog": {
              "act_code": 554,
              "ext": "t:31|pos:1_32|c_type:31|cate:10103|page:1|type:25",
              "luicode": "",
              "fid": "106003type=25&t=3&disable_hot=1&filter_type=realtimehot",
              "lfid": "",
              "uicode": 10000003
            },
            "itemid": "hotword",
            "icon": "https://simg.s.weibo.com/20190429_new.png",
            "desc_extr": "159110",
            "card_type": 4,
            "scheme": "https://m.weibo.cn/search?containerid=100103type%3D1%26t%3D10%26q%3D%E6%B0%91%E8%90%A5%E4%BC%81%E4%B8%9A%E8%A6%81%E5%9C%A8%E4%B8%8D%E6%96%AD%E7%A0%B4%E8%A7%A3%E9%9A%BE%E9%A2%98%E4%B8%AD%E5%89%8D%E8%BF%9B&isnewpage=1&extparam=cate%3D0%26pos%3D32%26realpos%3D32%26flag%3D1%26filter_type%3Drealtimehot%26c_type%3D31%26display_time%3D1590252475&luicode=10000011&lfid=106003type%3D25%26t%3D3%26disable_hot%3D1%26filter_type%3Drealtimehot",
            "desc": "民营企业要在不断破解难题中前进",
            "pic": "https://simg.s.weibo.com/20170303_img_search_33.png"
          },
          {
            "actionlog": {
              "act_code": 554,
              "ext": "t:31|pos:1_33|c_type:31|cate:10103|page:1|type:25",
              "luicode": "",
              "fid": "106003type=25&t=3&disable_hot=1&filter_type=realtimehot",
              "lfid": "",
              "uicode": 10000003
            },
            "desc_extr": "152875",
            "pic": "https://simg.s.weibo.com/20170303_img_search_34.png",
            "card_type": 4,
            "scheme": "https://m.weibo.cn/search?containerid=100103type%3D1%26t%3D10%26q%3D%23%E6%89%8B%E6%9C%BA%E5%A4%87%E5%BF%98%E5%BD%95%E9%87%8C%E9%83%BD%E5%86%99%E4%BA%86%E4%BB%80%E4%B9%88%23&isnewpage=1&extparam=cate%3D0%26pos%3D33%26realpos%3D33%26flag%3D0%26filter_type%3Drealtimehot%26c_type%3D31%26display_time%3D1590252475&luicode=10000011&lfid=106003type%3D25%26t%3D3%26disable_hot%3D1%26filter_type%3Drealtimehot",
            "desc": "手机备忘录里都写了什么",
            "itemid": "hotword"
          },
          {
            "actionlog": {
              "act_code": 554,
              "ext": "t:31|pos:1_34|c_type:31|cate:10103|page:1|type:25",
              "luicode": "",
              "fid": "106003type=25&t=3&disable_hot=1&filter_type=realtimehot",
              "lfid": "",
              "uicode": 10000003
            },
            "desc_extr": "149838",
            "pic": "https://simg.s.weibo.com/20170303_img_search_35.png",
            "card_type": 4,
            "scheme": "https://m.weibo.cn/search?containerid=100103type%3D1%26t%3D10%26q%3D%E8%88%9E%E8%80%85&isnewpage=1&extparam=cate%3D0%26pos%3D34%26realpos%3D34%26flag%3D0%26filter_type%3Drealtimehot%26c_type%3D31%26display_time%3D1590252475&luicode=10000011&lfid=106003type%3D25%26t%3D3%26disable_hot%3D1%26filter_type%3Drealtimehot",
            "desc": "舞者",
            "itemid": "hotword"
          },
          {
            "actionlog": {
              "act_code": 554,
              "ext": "t:31|pos:1_35|c_type:31|cate:10103|page:1|type:25",
              "luicode": "",
              "fid": "106003type=25&t=3&disable_hot=1&filter_type=realtimehot",
              "lfid": "",
              "uicode": 10000003
            },
            "desc_extr": "127348",
            "pic": "https://simg.s.weibo.com/20170303_img_search_36.png",
            "card_type": 4,
            "scheme": "https://m.weibo.cn/search?containerid=100103type%3D1%26t%3D10%26q%3D%E9%97%B0%E5%9B%9B%E6%9C%88&isnewpage=1&extparam=cate%3D0%26pos%3D35%26realpos%3D35%26flag%3D0%26filter_type%3Drealtimehot%26c_type%3D31%26display_time%3D1590252475&luicode=10000011&lfid=106003type%3D25%26t%3D3%26disable_hot%3D1%26filter_type%3Drealtimehot",
            "desc": "闰四月",
            "itemid": "hotword"
          },
          {
            "actionlog": {
              "act_code": 554,
              "ext": "t:31|pos:1_36|c_type:31|cate:10103|page:1|type:25",
              "luicode": "",
              "fid": "106003type=25&t=3&disable_hot=1&filter_type=realtimehot",
              "lfid": "",
              "uicode": 10000003
            },
            "desc_extr": "122162",
            "pic": "https://simg.s.weibo.com/20170303_img_search_37.png",
            "card_type": 4,
            "scheme": "https://m.weibo.cn/search?containerid=100103type%3D1%26t%3D10%26q%3D%23%E8%9D%B4%E8%9D%B6%E8%90%BD%E5%88%B0%E4%BA%86%E7%8B%97%E7%8B%97%E9%BC%BB%E5%AD%90%E4%B8%8A%23&isnewpage=1&extparam=cate%3D0%26pos%3D36%26realpos%3D36%26flag%3D0%26filter_type%3Drealtimehot%26c_type%3D31%26display_time%3D1590252475&luicode=10000011&lfid=106003type%3D25%26t%3D3%26disable_hot%3D1%26filter_type%3Drealtimehot",
            "desc": "蝴蝶落到了狗狗鼻子上",
            "itemid": "hotword"
          },
          {
            "actionlog": {
              "act_code": 554,
              "ext": "t:31|pos:1_37|c_type:31|cate:10103|page:1|type:25",
              "luicode": "",
              "fid": "106003type=25&t=3&disable_hot=1&filter_type=realtimehot",
              "lfid": "",
              "uicode": 10000003
            },
            "desc_extr": "121633",
            "pic": "https://simg.s.weibo.com/20170303_img_search_38.png",
            "card_type": 4,
            "scheme": "https://m.weibo.cn/search?containerid=100103type%3D1%26t%3D10%26q%3D%23%E4%B9%8C%E9%B8%A6%E7%9D%A3%E4%BF%83%E6%85%A2%E6%80%A7%E5%AD%90%E5%88%BA%E7%8C%AC%E8%BF%87%E9%A9%AC%E8%B7%AF%23&isnewpage=1&extparam=cate%3D0%26pos%3D37%26realpos%3D37%26flag%3D0%26filter_type%3Drealtimehot%26c_type%3D31%26display_time%3D1590252475&luicode=10000011&lfid=106003type%3D25%26t%3D3%26disable_hot%3D1%26filter_type%3Drealtimehot",
            "desc": "乌鸦督促慢性子刺猬过马路",
            "itemid": "hotword"
          },
          {
            "actionlog": {
              "act_code": 554,
              "ext": "t:31|pos:1_38|c_type:31|cate:10103|page:1|type:25",
              "luicode": "",
              "fid": "106003type=25&t=3&disable_hot=1&filter_type=realtimehot",
              "lfid": "",
              "uicode": 10000003
            },
            "desc_extr": "120244",
            "pic": "https://simg.s.weibo.com/20170303_img_search_39.png",
            "card_type": 4,
            "scheme": "https://m.weibo.cn/search?containerid=100103type%3D1%26t%3D10%26q%3D%E5%B1%B1%E4%B8%9C%E5%86%B0%E9%9B%B9&isnewpage=1&extparam=cate%3D0%26pos%3D38%26realpos%3D38%26flag%3D0%26filter_type%3Drealtimehot%26c_type%3D31%26display_time%3D1590252475&luicode=10000011&lfid=106003type%3D25%26t%3D3%26disable_hot%3D1%26filter_type%3Drealtimehot",
            "desc": "山东冰雹",
            "itemid": "hotword"
          },
          {
            "actionlog": {
              "act_code": 554,
              "ext": "t:31|pos:1_39|c_type:31|cate:10103|page:1|type:25",
              "luicode": "",
              "fid": "106003type=25&t=3&disable_hot=1&filter_type=realtimehot",
              "lfid": "",
              "uicode": 10000003
            },
            "desc_extr": "116614",
            "pic": "https://simg.s.weibo.com/20170303_img_search_40.png",
            "card_type": 4,
            "scheme": "https://m.weibo.cn/search?containerid=100103type%3D1%26t%3D10%26q%3D%23%E5%BD%93%E4%B8%87%E4%BA%A9%E6%A8%B1%E8%8A%B1%E5%9B%AD%E9%81%87%E4%B8%8A%E4%B8%AD%E5%9B%BD%E5%A4%A9%E7%9C%BC%23&isnewpage=1&extparam=cate%3D0%26pos%3D39%26realpos%3D39%26flag%3D0%26filter_type%3Drealtimehot%26c_type%3D31%26display_time%3D1590252475&luicode=10000011&lfid=106003type%3D25%26t%3D3%26disable_hot%3D1%26filter_type%3Drealtimehot",
            "desc": "当万亩樱花园遇上中国天眼",
            "itemid": "hotword"
          },
          {
            "actionlog": {
              "act_code": 554,
              "ext": "t:31|pos:1_40|c_type:31|cate:10103|page:1|type:25",
              "luicode": "",
              "fid": "106003type=25&t=3&disable_hot=1&filter_type=realtimehot",
              "lfid": "",
              "uicode": 10000003
            },
            "desc_extr": "106103",
            "pic": "https://simg.s.weibo.com/20170303_img_search_41.png",
            "card_type": 4,
            "scheme": "https://m.weibo.cn/search?containerid=100103type%3D1%26t%3D10%26q%3D%23%E4%B8%AD%E5%9B%BD%E7%AC%AC%E4%B8%80%E4%B8%AA%E5%9B%BD%E5%AE%B6%E5%85%AC%E5%9B%AD%23&isnewpage=1&extparam=cate%3D0%26pos%3D40%26realpos%3D40%26flag%3D0%26filter_type%3Drealtimehot%26c_type%3D31%26display_time%3D1590252475&luicode=10000011&lfid=106003type%3D25%26t%3D3%26disable_hot%3D1%26filter_type%3Drealtimehot",
            "desc": "中国第一个国家公园",
            "itemid": "hotword"
          },
          {
            "actionlog": {
              "act_code": 554,
              "ext": "t:31|pos:1_41|c_type:31|cate:10103|page:1|type:25",
              "luicode": "",
              "fid": "106003type=25&t=3&disable_hot=1&filter_type=realtimehot",
              "lfid": "",
              "uicode": 10000003
            },
            "desc_extr": "103293",
            "pic": "https://simg.s.weibo.com/20170303_img_search_42.png",
            "card_type": 4,
            "scheme": "https://m.weibo.cn/search?containerid=100103type%3D1%26t%3D10%26q%3D%23%E5%BC%A0%E6%96%87%E5%AE%8F%E7%A7%B0%E5%85%A8%E7%90%83%E7%96%AB%E6%83%85%E5%8F%AF%E8%83%BD%E8%A6%81%E8%BF%9E%E7%BB%AD%E4%B8%80%E5%88%B0%E4%B8%A4%E5%B9%B4%23&isnewpage=1&extparam=cate%3D0%26pos%3D41%26realpos%3D41%26flag%3D0%26filter_type%3Drealtimehot%26c_type%3D31%26display_time%3D1590252475&luicode=10000011&lfid=106003type%3D25%26t%3D3%26disable_hot%3D1%26filter_type%3Drealtimehot",
            "desc": "张文宏称全球疫情可能要连续一到两年",
            "itemid": "hotword"
          },
          {
            "actionlog": {
              "act_code": 554,
              "ext": "t:31|pos:1_42|c_type:31|cate:10103|page:1|type:25",
              "luicode": "",
              "fid": "106003type=25&t=3&disable_hot=1&filter_type=realtimehot",
              "lfid": "",
              "uicode": 10000003
            },
            "desc_extr": "94056",
            "pic": "https://simg.s.weibo.com/20170303_img_search_43.png",
            "card_type": 4,
            "scheme": "https://m.weibo.cn/search?containerid=100103type%3D1%26t%3D10%26q%3D%E8%8E%AB%E6%96%AF%E7%A7%91%E5%B8%82%E4%B8%AD%E5%BF%83%E5%8F%91%E7%94%9F%E5%8A%AB%E6%8C%81%E4%BA%BA%E8%B4%A8%E4%BA%8B%E4%BB%B6&isnewpage=1&extparam=cate%3D0%26pos%3D42%26realpos%3D42%26flag%3D0%26filter_type%3Drealtimehot%26c_type%3D31%26display_time%3D1590252475&luicode=10000011&lfid=106003type%3D25%26t%3D3%26disable_hot%3D1%26filter_type%3Drealtimehot",
            "desc": "莫斯科市中心发生劫持人质事件",
            "itemid": "hotword"
          },
          {
            "actionlog": {
              "act_code": 554,
              "ext": "t:31|pos:1_43|c_type:31|cate:10103|page:1|type:25",
              "luicode": "",
              "fid": "106003type=25&t=3&disable_hot=1&filter_type=realtimehot",
              "lfid": "",
              "uicode": 10000003
            },
            "desc_extr": "92197",
            "pic": "https://simg.s.weibo.com/20170303_img_search_44.png",
            "card_type": 4,
            "scheme": "https://m.weibo.cn/search?containerid=100103type%3D1%26t%3D10%26q%3D%E5%BC%A0%E6%96%87%E5%AE%8F%E8%B0%88%E5%A6%82%E4%BD%95%E6%AD%A3%E7%A1%AE%E4%BD%BF%E7%94%A8%E7%A9%BA%E8%B0%83&isnewpage=1&extparam=cate%3D0%26pos%3D43%26realpos%3D43%26flag%3D0%26filter_type%3Drealtimehot%26c_type%3D31%26display_time%3D1590252475&luicode=10000011&lfid=106003type%3D25%26t%3D3%26disable_hot%3D1%26filter_type%3Drealtimehot",
            "desc": "张文宏谈如何正确使用空调",
            "itemid": "hotword"
          },
          {
            "actionlog": {
              "act_code": 554,
              "ext": "t:31|pos:1_44|c_type:31|cate:10103|page:1|type:25",
              "luicode": "",
              "fid": "106003type=25&t=3&disable_hot=1&filter_type=realtimehot",
              "lfid": "",
              "uicode": 10000003
            },
            "desc_extr": "91104",
            "pic": "https://simg.s.weibo.com/20170303_img_search_45.png",
            "card_type": 4,
            "scheme": "https://m.weibo.cn/search?containerid=100103type%3D1%26t%3D10%26q%3D%23%E5%B7%B4%E5%9D%A0%E6%9C%BA%E4%BA%8B%E6%95%85%E6%89%BE%E5%88%B097%E5%85%B7%E9%81%97%E4%BD%93%23&isnewpage=1&extparam=cate%3D0%26pos%3D44%26realpos%3D44%26flag%3D0%26filter_type%3Drealtimehot%26c_type%3D31%26display_time%3D1590252475&luicode=10000011&lfid=106003type%3D25%26t%3D3%26disable_hot%3D1%26filter_type%3Drealtimehot",
            "desc": "巴坠机事故找到97具遗体",
            "itemid": "hotword"
          },
          {
            "actionlog": {
              "act_code": 554,
              "ext": "t:31|pos:1_45|c_type:31|cate:10103|page:1|type:25",
              "luicode": "",
              "fid": "106003type=25&t=3&disable_hot=1&filter_type=realtimehot",
              "lfid": "",
              "uicode": 10000003
            },
            "desc_extr": "89223",
            "pic": "https://simg.s.weibo.com/20170303_img_search_46.png",
            "card_type": 4,
            "scheme": "https://m.weibo.cn/search?containerid=100103type%3D1%26t%3D10%26q%3D%23%E4%BD%A0%E5%92%8C%E5%90%8C%E5%AD%A6%E5%9C%A8%E6%95%99%E5%AE%A4%E7%9A%84%E6%A0%B7%E5%AD%90%23&isnewpage=1&extparam=cate%3D0%26pos%3D45%26realpos%3D45%26flag%3D0%26filter_type%3Drealtimehot%26c_type%3D31%26display_time%3D1590252475&luicode=10000011&lfid=106003type%3D25%26t%3D3%26disable_hot%3D1%26filter_type%3Drealtimehot",
            "desc": "你和同学在教室的样子",
            "itemid": "hotword"
          },
          {
            "actionlog": {
              "act_code": 554,
              "ext": "t:31|pos:1_46|c_type:31|cate:10103|page:1|type:25",
              "luicode": "",
              "fid": "106003type=25&t=3&disable_hot=1&filter_type=realtimehot",
              "lfid": "",
              "uicode": 10000003
            },
            "desc_extr": "87936",
            "pic": "https://simg.s.weibo.com/20170303_img_search_47.png",
            "card_type": 4,
            "scheme": "https://m.weibo.cn/search?containerid=100103type%3D1%26t%3D10%26q%3D%23%E5%81%87%E5%A6%82%E5%A9%B4%E5%84%BF%E6%9C%89%E4%BA%86%E7%89%99%E9%BD%BF%23&isnewpage=1&extparam=cate%3D0%26pos%3D46%26realpos%3D46%26flag%3D0%26filter_type%3Drealtimehot%26c_type%3D31%26display_time%3D1590252475&luicode=10000011&lfid=106003type%3D25%26t%3D3%26disable_hot%3D1%26filter_type%3Drealtimehot",
            "desc": "假如婴儿有了牙齿",
            "itemid": "hotword"
          },
          {
            "actionlog": {
              "act_code": 554,
              "ext": "t:31|pos:1_47|c_type:31|cate:10103|page:1|type:25",
              "luicode": "",
              "fid": "106003type=25&t=3&disable_hot=1&filter_type=realtimehot",
              "lfid": "",
              "uicode": 10000003
            },
            "desc_extr": "87917",
            "pic": "https://simg.s.weibo.com/20170303_img_search_48.png",
            "card_type": 4,
            "scheme": "https://m.weibo.cn/search?containerid=100103type%3D1%26t%3D10%26q%3D%23%E6%9D%8E%E7%8E%B0%E5%86%B2%E6%B5%AA%23&isnewpage=1&extparam=cate%3D0%26pos%3D47%26realpos%3D47%26flag%3D0%26filter_type%3Drealtimehot%26c_type%3D31%26display_time%3D1590252475&luicode=10000011&lfid=106003type%3D25%26t%3D3%26disable_hot%3D1%26filter_type%3Drealtimehot",
            "desc": "李现冲浪",
            "itemid": "hotword"
          },
          {
            "actionlog": {
              "act_code": 554,
              "ext": "t:31|pos:1_48|c_type:31|cate:10103|page:1|type:25",
              "luicode": "",
              "fid": "106003type=25&t=3&disable_hot=1&filter_type=realtimehot",
              "lfid": "",
              "uicode": 10000003
            },
            "desc_extr": "67138",
            "pic": "https://simg.s.weibo.com/20170303_img_search_49.png",
            "card_type": 4,
            "scheme": "https://m.weibo.cn/search?containerid=100103type%3D1%26t%3D10%26q%3D%E6%81%B6%E9%AD%94%E4%B9%8B%E7%9C%BC%E8%89%BE%E8%82%AF%E6%B3%89&isnewpage=1&extparam=cate%3D0%26pos%3D48%26realpos%3D48%26flag%3D0%26filter_type%3Drealtimehot%26c_type%3D31%26display_time%3D1590252475&luicode=10000011&lfid=106003type%3D25%26t%3D3%26disable_hot%3D1%26filter_type%3Drealtimehot",
            "desc": "恶魔之眼艾肯泉",
            "itemid": "hotword"
          },
          {
            "actionlog": {
              "act_code": 554,
              "ext": "t:31|pos:1_49|c_type:31|cate:10103|page:1|type:25",
              "luicode": "",
              "fid": "106003type=25&t=3&disable_hot=1&filter_type=realtimehot",
              "lfid": "",
              "uicode": 10000003
            },
            "desc_extr": "52717",
            "pic": "https://simg.s.weibo.com/20170303_img_search_50.png",
            "card_type": 4,
            "scheme": "https://m.weibo.cn/search?containerid=100103type%3D1%26t%3D10%26q%3D%23%E5%B0%8F%E6%97%B6%E5%80%99%E5%85%B3%E4%BA%8E%E5%A4%8F%E5%A4%A9%E7%9A%84%E8%AE%B0%E5%BF%86%23&isnewpage=1&extparam=cate%3D0%26pos%3D49%26realpos%3D49%26flag%3D0%26filter_type%3Drealtimehot%26c_type%3D31%26display_time%3D1590252475&luicode=10000011&lfid=106003type%3D25%26t%3D3%26disable_hot%3D1%26filter_type%3Drealtimehot",
            "desc": "小时候关于夏天的记忆",
            "itemid": "hotword"
          }
        ]
      },
      {
        "card_type": 11,
        "title": "实时上升热点",
        "show_type": 0,
        "card_group": [
          {
            "actionlog": {
              "act_code": 554,
              "ext": "t:25|pos:1_1|c_type:25|cate:10103|prop:0|page:1|type:25",
              "luicode": "",
              "fid": "106003type=25&t=3&disable_hot=1&filter_type=realtimehot",
              "lfid": "",
              "uicode": 10000003
            },
            "desc_extr": 23931,
            "pic": "https://simg.s.weibo.com/20170306_plus_new1.png",
            "card_type": 4,
            "scheme": "https://m.weibo.cn/search?containerid=100103type%3D1%26t%3D10%26q%3D%23%E6%81%8B%E7%88%B1%E4%B8%AD%E9%81%87%E5%88%B0%E6%9B%B4%E5%A5%BD%E7%9A%84%E4%BA%BA%E6%80%8E%E4%B9%88%E5%8A%9E%23&isnewpage=1&extparam=pos%3D0%26q%3D%2523%25E6%2581%258B%25E7%2588%25B1%25E4%25B8%25AD%25E9%2581%2587%25E5%2588%25B0%25E6%259B%25B4%25E5%25A5%25BD%25E7%259A%2584%25E4%25BA%25BA%25E6%2580%258E%25E4%25B9%2588%25E5%258A%259E%2523%26mi_cid%3D100103%26c_type%3D25%26filter_type%3Dpersonal%26cate%3D%26display_time%3D1590252475&luicode=10000011&lfid=106003type%3D25%26t%3D3%26disable_hot%3D1%26filter_type%3Drealtimehot",
            "desc": "恋爱中遇到更好的人怎么办",
            "itemid": "realtimehotspotcon"
          },
          {
            "actionlog": {
              "act_code": 554,
              "ext": "t:25|pos:1_2|c_type:25|cate:10103|prop:0|page:1|type:25",
              "luicode": "",
              "fid": "106003type=25&t=3&disable_hot=1&filter_type=realtimehot",
              "lfid": "",
              "uicode": 10000003
            },
            "desc_extr": 24442,
            "pic": "https://simg.s.weibo.com/20170306_plus_new1.png",
            "card_type": 4,
            "scheme": "https://m.weibo.cn/search?containerid=100103type%3D1%26t%3D10%26q%3D%23%E6%B2%99%E6%BC%A0%E4%B9%8B%E5%9F%8E%E6%95%A6%E7%85%8C%E6%9C%89%E5%A4%9A%E8%BF%B7%E4%BA%BA%23&isnewpage=1&extparam=pos%3D1%26q%3D%2523%25E6%25B2%2599%25E6%25BC%25A0%25E4%25B9%258B%25E5%259F%258E%25E6%2595%25A6%25E7%2585%258C%25E6%259C%2589%25E5%25A4%259A%25E8%25BF%25B7%25E4%25BA%25BA%2523%26mi_cid%3D100103%26c_type%3D25%26filter_type%3Dpersonal%26cate%3D%26display_time%3D1590252475&luicode=10000011&lfid=106003type%3D25%26t%3D3%26disable_hot%3D1%26filter_type%3Drealtimehot",
            "desc": "沙漠之城敦煌有多迷人",
            "itemid": "realtimehotspotcon"
          },
          {
            "actionlog": {
              "act_code": 554,
              "ext": "t:25|pos:1_3|c_type:25|cate:10103|prop:0|page:1|type:25",
              "luicode": "",
              "fid": "106003type=25&t=3&disable_hot=1&filter_type=realtimehot",
              "lfid": "",
              "uicode": 10000003
            },
            "desc_extr": 24027,
            "pic": "https://simg.s.weibo.com/20170306_plus_new1.png",
            "card_type": 4,
            "scheme": "https://m.weibo.cn/search?containerid=100103type%3D1%26t%3D10%26q%3D%23%E7%8C%AB%E5%92%AA%E8%BF%B7%E6%83%91%E8%A1%8C%E4%B8%BA%E5%9B%BE%E9%89%B4%23&isnewpage=1&extparam=pos%3D2%26q%3D%2523%25E7%258C%25AB%25E5%2592%25AA%25E8%25BF%25B7%25E6%2583%2591%25E8%25A1%258C%25E4%25B8%25BA%25E5%259B%25BE%25E9%2589%25B4%2523%26mi_cid%3D100103%26c_type%3D25%26filter_type%3Dpersonal%26cate%3D%26display_time%3D1590252475&luicode=10000011&lfid=106003type%3D25%26t%3D3%26disable_hot%3D1%26filter_type%3Drealtimehot",
            "desc": "猫咪迷惑行为图鉴",
            "itemid": "realtimehotspotcon"
          },
          {
            "actionlog": {
              "act_code": 554,
              "ext": "t:25|pos:1_4|c_type:25|cate:10103|prop:0|page:1|type:25",
              "luicode": "",
              "fid": "106003type=25&t=3&disable_hot=1&filter_type=realtimehot",
              "lfid": "",
              "uicode": 10000003
            },
            "desc_extr": 24970,
            "pic": "https://simg.s.weibo.com/20170306_plus_new1.png",
            "card_type": 4,
            "scheme": "https://m.weibo.cn/search?containerid=100103type%3D1%26t%3D10%26q%3D%23%E6%9C%8B%E5%8F%8B%E5%9C%88%E5%BC%8F%E4%BA%A4%E5%8F%8B%E7%9B%B8%E4%BA%B2%23&isnewpage=1&extparam=pos%3D3%26q%3D%2523%25E6%259C%258B%25E5%258F%258B%25E5%259C%2588%25E5%25BC%258F%25E4%25BA%25A4%25E5%258F%258B%25E7%259B%25B8%25E4%25BA%25B2%2523%26mi_cid%3D100103%26c_type%3D25%26filter_type%3Dpersonal%26cate%3D%26display_time%3D1590252475&luicode=10000011&lfid=106003type%3D25%26t%3D3%26disable_hot%3D1%26filter_type%3Drealtimehot",
            "desc": "朋友圈式交友相亲",
            "itemid": "realtimehotspotcon"
          },
          {
            "actionlog": {
              "act_code": 554,
              "ext": "t:25|pos:1_5|c_type:25|cate:10103|prop:0|page:1|type:25",
              "luicode": "",
              "fid": "106003type=25&t=3&disable_hot=1&filter_type=realtimehot",
              "lfid": "",
              "uicode": 10000003
            },
            "desc_extr": 24712,
            "pic": "https://simg.s.weibo.com/20170306_plus_new1.png",
            "card_type": 4,
            "scheme": "https://m.weibo.cn/search?containerid=100103type%3D1%26t%3D10%26q%3D%23%E6%9C%80%E7%90%86%E6%83%B3%E7%8A%B6%E6%80%81%E7%9A%84%E5%A4%AB%E5%A6%BB%E5%85%B3%E7%B3%BB%23&isnewpage=1&extparam=pos%3D4%26q%3D%2523%25E6%259C%2580%25E7%2590%2586%25E6%2583%25B3%25E7%258A%25B6%25E6%2580%2581%25E7%259A%2584%25E5%25A4%25AB%25E5%25A6%25BB%25E5%2585%25B3%25E7%25B3%25BB%2523%26mi_cid%3D100103%26c_type%3D25%26filter_type%3Dpersonal%26cate%3D%26display_time%3D1590252475&luicode=10000011&lfid=106003type%3D25%26t%3D3%26disable_hot%3D1%26filter_type%3Drealtimehot",
            "desc": "最理想状态的夫妻关系",
            "itemid": "realtimehotspotcon"
          },
          {
            "actionlog": {
              "act_code": 554,
              "ext": "t:25|pos:1_6|c_type:25|cate:10103|prop:0|page:1|type:25",
              "luicode": "",
              "fid": "106003type=25&t=3&disable_hot=1&filter_type=realtimehot",
              "lfid": "",
              "uicode": 10000003
            },
            "desc_extr": 18155,
            "pic": "https://simg.s.weibo.com/20170306_plus_new1.png",
            "card_type": 4,
            "scheme": "https://m.weibo.cn/search?containerid=100103type%3D1%26t%3D10%26q%3D%E5%B7%A5%E4%BA%BA%E7%99%BE%E7%B1%B3%E9%AB%98%E7%A9%BA4%E5%B0%8F%E6%97%B6%E8%B5%B07%E5%85%AC%E9%87%8C&isnewpage=1&extparam=pos%3D5%26q%3D%25E5%25B7%25A5%25E4%25BA%25BA%25E7%2599%25BE%25E7%25B1%25B3%25E9%25AB%2598%25E7%25A9%25BA4%25E5%25B0%258F%25E6%2597%25B6%25E8%25B5%25B07%25E5%2585%25AC%25E9%2587%258C%26mi_cid%3D100103%26c_type%3D25%26filter_type%3Dpersonal%26cate%3D%26display_time%3D1590252475&luicode=10000011&lfid=106003type%3D25%26t%3D3%26disable_hot%3D1%26filter_type%3Drealtimehot",
            "desc": "工人百米高空4小时走7公里",
            "itemid": "realtimehotspotcon"
          },
          {
            "actionlog": {
              "act_code": 554,
              "ext": "t:25|pos:1_7|c_type:25|cate:10103|prop:0|page:1|type:25",
              "luicode": "",
              "fid": "106003type=25&t=3&disable_hot=1&filter_type=realtimehot",
              "lfid": "",
              "uicode": 10000003
            },
            "desc_extr": 25711,
            "pic": "https://simg.s.weibo.com/20170306_plus_new1.png",
            "card_type": 4,
            "scheme": "https://m.weibo.cn/search?containerid=100103type%3D1%26t%3D10%26q%3D%23%E4%BB%80%E4%B9%88%E6%A0%B7%E7%9A%84%E5%A5%B3%E7%94%9F%E4%B8%80%E7%9C%8B%E5%B0%B1%E9%9A%BE%E8%BF%BD%23&isnewpage=1&extparam=pos%3D6%26q%3D%2523%25E4%25BB%2580%25E4%25B9%2588%25E6%25A0%25B7%25E7%259A%2584%25E5%25A5%25B3%25E7%2594%259F%25E4%25B8%2580%25E7%259C%258B%25E5%25B0%25B1%25E9%259A%25BE%25E8%25BF%25BD%2523%26mi_cid%3D100103%26c_type%3D25%26filter_type%3Dpersonal%26cate%3D%26display_time%3D1590252475&luicode=10000011&lfid=106003type%3D25%26t%3D3%26disable_hot%3D1%26filter_type%3Drealtimehot",
            "desc": "什么样的女生一看就难追",
            "itemid": "realtimehotspotcon"
          },
          {
            "actionlog": {
              "act_code": 554,
              "ext": "t:25|pos:1_8|c_type:25|cate:10103|prop:0|page:1|type:25",
              "luicode": "",
              "fid": "106003type=25&t=3&disable_hot=1&filter_type=realtimehot",
              "lfid": "",
              "uicode": 10000003
            },
            "desc_extr": 17719,
            "pic": "https://simg.s.weibo.com/20170306_plus_new1.png",
            "card_type": 4,
            "scheme": "https://m.weibo.cn/search?containerid=100103type%3D1%26t%3D10%26q%3D%23%E5%AD%A6%E7%94%9F%E6%97%B6%E4%BB%A3%E8%B5%9A%E7%9A%84%E7%AC%AC%E4%B8%80%E6%A1%B6%E9%87%91%23&isnewpage=1&extparam=pos%3D7%26q%3D%2523%25E5%25AD%25A6%25E7%2594%259F%25E6%2597%25B6%25E4%25BB%25A3%25E8%25B5%259A%25E7%259A%2584%25E7%25AC%25AC%25E4%25B8%2580%25E6%25A1%25B6%25E9%2587%2591%2523%26mi_cid%3D100103%26c_type%3D25%26filter_type%3Dpersonal%26cate%3D%26display_time%3D1590252475&luicode=10000011&lfid=106003type%3D25%26t%3D3%26disable_hot%3D1%26filter_type%3Drealtimehot",
            "desc": "学生时代赚的第一桶金",
            "itemid": "realtimehotspotcon"
          },
          {
            "actionlog": {
              "act_code": 554,
              "ext": "t:25|pos:1_9|c_type:25|cate:10103|prop:0|page:1|type:25",
              "luicode": "",
              "fid": "106003type=25&t=3&disable_hot=1&filter_type=realtimehot",
              "lfid": "",
              "uicode": 10000003
            },
            "desc_extr": 24713,
            "pic": "https://simg.s.weibo.com/20170306_plus_new1.png",
            "card_type": 4,
            "scheme": "https://m.weibo.cn/search?containerid=100103type%3D1%26t%3D10%26q%3D%23%E6%89%93%E6%B6%88%E6%81%8B%E7%88%B1%E5%BF%B5%E5%A4%B4%E7%9A%84%E6%A0%B9%E6%9C%AC%E5%8E%9F%E5%9B%A0%23&isnewpage=1&extparam=pos%3D8%26q%3D%2523%25E6%2589%2593%25E6%25B6%2588%25E6%2581%258B%25E7%2588%25B1%25E5%25BF%25B5%25E5%25A4%25B4%25E7%259A%2584%25E6%25A0%25B9%25E6%259C%25AC%25E5%258E%259F%25E5%259B%25A0%2523%26mi_cid%3D100103%26c_type%3D25%26filter_type%3Dpersonal%26cate%3D%26display_time%3D1590252475&luicode=10000011&lfid=106003type%3D25%26t%3D3%26disable_hot%3D1%26filter_type%3Drealtimehot",
            "desc": "打消恋爱念头的根本原因",
            "itemid": "realtimehotspotcon"
          },
          {
            "actionlog": {
              "act_code": 554,
              "ext": "t:25|pos:1_10|c_type:25|cate:10103|prop:0|page:1|type:25",
              "luicode": "",
              "fid": "106003type=25&t=3&disable_hot=1&filter_type=realtimehot",
              "lfid": "",
              "uicode": 10000003
            },
            "desc_extr": 24997,
            "pic": "https://simg.s.weibo.com/20170306_plus_new1.png",
            "card_type": 4,
            "scheme": "https://m.weibo.cn/search?containerid=100103type%3D1%26t%3D10%26q%3D%23%E4%BD%A0%E5%9B%A0%E4%B8%BA%E6%80%95%E9%AC%BC%E5%81%9A%E8%BF%87%E5%93%AA%E4%BA%9B%E5%82%BB%E4%BA%8B%23&isnewpage=1&extparam=pos%3D9%26q%3D%2523%25E4%25BD%25A0%25E5%259B%25A0%25E4%25B8%25BA%25E6%2580%2595%25E9%25AC%25BC%25E5%2581%259A%25E8%25BF%2587%25E5%2593%25AA%25E4%25BA%259B%25E5%2582%25BB%25E4%25BA%258B%2523%26mi_cid%3D100103%26c_type%3D25%26filter_type%3Dpersonal%26cate%3D%26display_time%3D1590252475&luicode=10000011&lfid=106003type%3D25%26t%3D3%26disable_hot%3D1%26filter_type%3Drealtimehot",
            "desc": "你因为怕鬼做过哪些傻事",
            "itemid": "realtimehotspotcon"
          },
          {
            "actionlog": {
              "act_code": 554,
              "ext": "t:25|pos:1_11|c_type:25|cate:10103|prop:0|page:1|type:25",
              "luicode": "",
              "fid": "106003type=25&t=3&disable_hot=1&filter_type=realtimehot",
              "lfid": "",
              "uicode": 10000003
            },
            "desc_extr": 24658,
            "pic": "https://simg.s.weibo.com/20170306_plus_new1.png",
            "card_type": 4,
            "scheme": "https://m.weibo.cn/search?containerid=100103type%3D1%26t%3D10%26q%3D%23%E6%9D%A0%E7%B2%BE%E6%98%AF%E6%80%8E%E4%B9%88%E4%BA%A7%E7%94%9F%E7%9A%84%23&isnewpage=1&extparam=pos%3D10%26q%3D%2523%25E6%259D%25A0%25E7%25B2%25BE%25E6%2598%25AF%25E6%2580%258E%25E4%25B9%2588%25E4%25BA%25A7%25E7%2594%259F%25E7%259A%2584%2523%26mi_cid%3D100103%26c_type%3D25%26filter_type%3Dpersonal%26cate%3D%26display_time%3D1590252475&luicode=10000011&lfid=106003type%3D25%26t%3D3%26disable_hot%3D1%26filter_type%3Drealtimehot",
            "desc": "杠精是怎么产生的",
            "itemid": "realtimehotspotcon"
          },
          {
            "actionlog": {
              "act_code": 554,
              "ext": "t:25|pos:1_12|c_type:25|cate:10103|prop:0|page:1|type:25",
              "luicode": "",
              "fid": "106003type=25&t=3&disable_hot=1&filter_type=realtimehot",
              "lfid": "",
              "uicode": 10000003
            },
            "desc_extr": 24912,
            "pic": "https://simg.s.weibo.com/20170306_plus_new1.png",
            "card_type": 4,
            "scheme": "https://m.weibo.cn/search?containerid=100103type%3D1%26t%3D10%26q%3D%23%E4%BB%96%E4%BA%BA%E6%B2%A1%E6%B3%95%E7%90%86%E8%A7%A3%E7%9A%84%E8%87%AA%E5%8D%91%E7%82%B9%23&isnewpage=1&extparam=pos%3D11%26q%3D%2523%25E4%25BB%2596%25E4%25BA%25BA%25E6%25B2%25A1%25E6%25B3%2595%25E7%2590%2586%25E8%25A7%25A3%25E7%259A%2584%25E8%2587%25AA%25E5%258D%2591%25E7%2582%25B9%2523%26mi_cid%3D100103%26c_type%3D25%26filter_type%3Dpersonal%26cate%3D%26display_time%3D1590252475&luicode=10000011&lfid=106003type%3D25%26t%3D3%26disable_hot%3D1%26filter_type%3Drealtimehot",
            "desc": "他人没法理解的自卑点",
            "itemid": "realtimehotspotcon"
          },
          {
            "actionlog": {
              "act_code": 554,
              "ext": "t:25|pos:1_13|c_type:25|cate:10103|prop:0|page:1|type:25",
              "luicode": "",
              "fid": "106003type=25&t=3&disable_hot=1&filter_type=realtimehot",
              "lfid": "",
              "uicode": 10000003
            },
            "desc_extr": 24406,
            "pic": "https://simg.s.weibo.com/20170306_plus_new1.png",
            "card_type": 4,
            "scheme": "https://m.weibo.cn/search?containerid=100103type%3D1%26t%3D10%26q%3D%23%E6%9A%97%E6%81%8B%E5%AF%B9%E6%96%B9%E7%9A%84%E7%90%86%E7%94%B1%23&isnewpage=1&extparam=pos%3D12%26q%3D%2523%25E6%259A%2597%25E6%2581%258B%25E5%25AF%25B9%25E6%2596%25B9%25E7%259A%2584%25E7%2590%2586%25E7%2594%25B1%2523%26mi_cid%3D100103%26c_type%3D25%26filter_type%3Dpersonal%26cate%3D%26display_time%3D1590252475&luicode=10000011&lfid=106003type%3D25%26t%3D3%26disable_hot%3D1%26filter_type%3Drealtimehot",
            "desc": "暗恋对方的理由",
            "itemid": "realtimehotspotcon"
          },
          {
            "actionlog": {
              "act_code": 554,
              "ext": "t:25|pos:1_14|c_type:25|cate:10103|prop:0|page:1|type:25",
              "luicode": "",
              "fid": "106003type=25&t=3&disable_hot=1&filter_type=realtimehot",
              "lfid": "",
              "uicode": 10000003
            },
            "desc_extr": 25570,
            "pic": "https://simg.s.weibo.com/20170306_plus_new1.png",
            "card_type": 4,
            "scheme": "https://m.weibo.cn/search?containerid=100103type%3D1%26t%3D10%26q%3D%23%E8%A7%81%E8%BF%87%E7%9C%9F%E5%AE%9E%E5%8F%88%E6%AF%81%E4%B8%89%E8%A7%82%E7%9A%84%E4%BA%8B%23&isnewpage=1&extparam=pos%3D13%26q%3D%2523%25E8%25A7%2581%25E8%25BF%2587%25E7%259C%259F%25E5%25AE%259E%25E5%258F%2588%25E6%25AF%2581%25E4%25B8%2589%25E8%25A7%2582%25E7%259A%2584%25E4%25BA%258B%2523%26mi_cid%3D100103%26c_type%3D25%26filter_type%3Dpersonal%26cate%3D%26display_time%3D1590252475&luicode=10000011&lfid=106003type%3D25%26t%3D3%26disable_hot%3D1%26filter_type%3Drealtimehot",
            "desc": "见过真实又毁三观的事",
            "itemid": "realtimehotspotcon"
          },
          {
            "actionlog": {
              "act_code": 554,
              "ext": "t:25|pos:1_15|c_type:25|cate:10103|prop:0|page:1|type:25",
              "luicode": "",
              "fid": "106003type=25&t=3&disable_hot=1&filter_type=realtimehot",
              "lfid": "",
              "uicode": 10000003
            },
            "desc_extr": 24705,
            "pic": "https://simg.s.weibo.com/20170306_plus_new1.png",
            "card_type": 4,
            "scheme": "https://m.weibo.cn/search?containerid=100103type%3D1%26t%3D10%26q%3D%23%E5%BD%93%E4%BB%A3%E4%BA%BA%E7%A4%BE%E4%BA%A4%E6%80%A7%E6%92%92%E8%B0%8E%E7%9A%84%E8%A1%A8%E7%8E%B0%23&isnewpage=1&extparam=pos%3D14%26q%3D%2523%25E5%25BD%2593%25E4%25BB%25A3%25E4%25BA%25BA%25E7%25A4%25BE%25E4%25BA%25A4%25E6%2580%25A7%25E6%2592%2592%25E8%25B0%258E%25E7%259A%2584%25E8%25A1%25A8%25E7%258E%25B0%2523%26mi_cid%3D100103%26c_type%3D25%26filter_type%3Dpersonal%26cate%3D%26display_time%3D1590252475&luicode=10000011&lfid=106003type%3D25%26t%3D3%26disable_hot%3D1%26filter_type%3Drealtimehot",
            "desc": "当代人社交性撒谎的表现",
            "itemid": "realtimehotspotcon"
          },
          {
            "actionlog": {
              "act_code": 554,
              "ext": "t:25|pos:1_16|c_type:25|cate:10103|prop:0|page:1|type:25",
              "luicode": "",
              "fid": "106003type=25&t=3&disable_hot=1&filter_type=realtimehot",
              "lfid": "",
              "uicode": 10000003
            },
            "desc_extr": 25363,
            "pic": "https://simg.s.weibo.com/20170306_plus_new1.png",
            "card_type": 4,
            "scheme": "https://m.weibo.cn/search?containerid=100103type%3D1%26t%3D10%26q%3D%23%E8%B0%A2%E5%8F%AF%E5%AF%85%E4%BA%BA%E9%97%B4%E6%8A%BC%E9%9F%B5%E6%9C%BA%23&isnewpage=1&extparam=pos%3D15%26q%3D%2523%25E8%25B0%25A2%25E5%258F%25AF%25E5%25AF%2585%25E4%25BA%25BA%25E9%2597%25B4%25E6%258A%25BC%25E9%259F%25B5%25E6%259C%25BA%2523%26mi_cid%3D100103%26c_type%3D25%26filter_type%3Dpersonal%26cate%3D%26display_time%3D1590252475&luicode=10000011&lfid=106003type%3D25%26t%3D3%26disable_hot%3D1%26filter_type%3Drealtimehot",
            "desc": "谢可寅人间押韵机",
            "itemid": "realtimehotspotcon"
          }
        ]
      },
      {
        "desc_extr": "好友圈的新鲜热点",
        "pic": "https://simg.s.weibo.com/20200414_%E5%A5%BD%E5%8F%8B%E7%83%AD%E6%90%9C%403x.png",
        "display_arrow": 1,
        "actionlog": {
          "act_code": 554,
          "ext": "t:113|pos:0|c_type:113|cate:10103|mpos:4|page:1|type:25",
          "luicode": "",
          "fid": "106003type=25&t=3&disable_hot=1&filter_type=realtimehot",
          "lfid": "",
          "uicode": ""
        },
        "scheme": "https://m.weibo.cn/p/index?containerid=106003type%3D25%26filter_type%3Dfriends&luicode=10000011&lfid=106003type%3D25%26t%3D3%26disable_hot%3D1%26filter_type%3Drealtimehot",
        "desc": "好友热搜",
        "card_type": 4
      }
    ],
    "pageInfo": {
      "page_size": 0,
      "can_shared": 0,
      "toolbar_menus": [
        {
          "actionlog": {
            "act_code": 554,
            "ext": "t:114|cate:10103|c_type:114|page:1|type:25",
            "luicode": "",
            "fid": "106003type=25&t=3&disable_hot=1&filter_type=realtimehot",
            "lfid": ""
          },
          "title_color_dark": "#EA8011",
          "params": {
            "scheme": "sinaweibo://abc"
          },
          "skip_format": 1,
          "pic": "https://simg.s.weibo.com/20200507_realtimehot_selected_default.png",
          "pic_dark": "https://simg.s.weibo.com/20200507_realtimehot_selected_dark.png",
          "title_color": "#FF8200",
          "name": "热搜榜",
          "type": "link",
          "scheme": "https://m.weibo.cn/feature/applink?scheme=sinaweibo%3A%2F%2Fabc"
        },
        {
          "actionlog": {
            "act_code": 554,
            "ext": "t:115|cate:10103|c_type:115|page:1|type:25",
            "luicode": "",
            "fid": "106003type=25&t=3&disable_hot=1&filter_type=realtimehot",
            "lfid": ""
          },
          "title_color_dark": "#999999",
          "params": {
            "scheme": "sinaweibo://pageinfo?containerid=106003type%3D25%26t%3D3%26disable_hot%3D1%26filter_type%3Dtopicscene&title=话题榜&extparam=lon%3D%26lat%3D"
          },
          "skip_format": 1,
          "pic": "https://simg.s.weibo.com/20200507_topicband_default.png",
          "pic_dark": "https://simg.s.weibo.com/20200507_topicband_dark.png",
          "title_color": "#333333",
          "name": "话题榜",
          "type": "link",
          "scheme": "https://m.weibo.cn/p/index?containerid=106003type%3D25%26t%3D3%26disable_hot%3D1%26filter_type%3Dtopicscene&title=%E8%AF%9D%E9%A2%98%E6%A6%9C&extparam=lon%3D%26lat%3D&luicode=10000011&lfid=106003type%3D25%26t%3D3%26disable_hot%3D1%26filter_type%3Drealtimehot"
        },
        {
          "actionlog": {
            "act_code": 554,
            "ext": "t:116|cate:10103|c_type:116|page:1|type:25",
            "luicode": "",
            "fid": "106003type=25&t=3&disable_hot=1&filter_type=realtimehot",
            "lfid": ""
          },
          "title_color_dark": "#999999",
          "params": {
            "scheme": "sinaweibo://pageinfo?containerid=106003type%3D25%26t%3D3%26disable_hot%3D1%26filter_type%3Dnewtimes&title=要闻榜&extparam=lon%3D%26lat%3D"
          },
          "skip_format": 1,
          "pic": "https://simg.s.weibo.com/20200507_newtimes_default.png",
          "pic_dark": "https://simg.s.weibo.com/20200507_newtimes_dark.png",
          "title_color": "#333333",
          "name": "要闻榜",
          "type": "link",
          "scheme": "https://m.weibo.cn/p/index?containerid=106003type%3D25%26t%3D3%26disable_hot%3D1%26filter_type%3Dnewtimes&title=%E8%A6%81%E9%97%BB%E6%A6%9C&extparam=lon%3D%26lat%3D&luicode=10000011&lfid=106003type%3D25%26t%3D3%26disable_hot%3D1%26filter_type%3Drealtimehot"
        }
      ],
      "cardlist_menus": [],
      "banner_info": {
        "auto_flow": 1,
        "height": 202,
        "flow_gap": 2,
        "card_type": 22,
        "pic_items": [
          {
            "scheme": "sinaweibo://abc",
            "pic": "https://simg.s.weibo.com/20200520_piaohong_banner.png"
          }
        ],
        "width": 750
      },
      "containerid": "106003type=25&t=3&disable_hot=1&filter_type=realtimehot",
      "show_style": 1,
      "total": 0,
      "page_title": "微博热搜",
      "starttime": 1590252475,
      "title_top": "微博热搜",
      "v_p": "42",
      "page_type": "08",
      "nick": "微博热搜",
      "background": null,
      "attitudes_count": 2,
      "attitudes_status": 0,
      "buttons": [
        {
          "type": "like",
          "sub_type": "",
          "name": "",
          "params": {
            "id": "106003type=25&t=3&disable_hot=1&filter_type=realtimehot",
            "type": "page"
          },
          "scheme": "/api/container/btn?module=like&containerid=106003type=25&t=3&disable_hot=1&filter_type=realtimehot"
        }
      ],
      "page": null
    },
    "banners": null,
    "scheme": "sinaweibo://pageinfo?containerid=106003type=25&t=3&disable_hot=1&filter_type=realtimehot&title=%E5%BE%AE%E5%8D%9A%E7%83%AD%E6%90%9C&extparam=cate%3D10103%26pos%3D0_0%26mi_cid%3D100103%26filter_type%3Drealtimehot%26c_type%3D30%26display_time%3D1590247150&luicode=10000011&lfid=231583&_T_WM=66337229921&v_p=42"
  }
}